scimap/__init__.py
scimap/__main__.py
scimap/cli/__init__.py
scimap/cli/_scimap_mcmicro.py
scimap/cli/test.py
scimap/dev/cluster.py
scimap/dev/find_optimal_radius.py
scimap/dev/image_viewer_vit.py
scimap/dev/phneotype_graph.csv
scimap/dev/roi_building.py
scimap/dev/spatial_interaction_plot.py
scimap/external/__init__.py
scimap/helpers/__init__.py
scimap/helpers/add_roi_scatter.py
scimap/helpers/addROI_omero.py
scimap/helpers/animate.py
scimap/helpers/classify.py
scimap/helpers/downloadDemoData.py
scimap/helpers/dropFeatures.py
scimap/helpers/merge_adata_obs.py
scimap/helpers/rename.py
scimap/helpers/scimap_to_csv.py
scimap/plotting/__init__.py
scimap/plotting/addROI_image.py
scimap/plotting/cluster_plots.py
scimap/plotting/densityPlot2D.py
scimap/plotting/distPlot.py
scimap/plotting/foldchange.py
scimap/plotting/gate_finder.py
scimap/plotting/groupCorrelation.py
scimap/plotting/heatmap.py
scimap/plotting/image_viewer.py
scimap/plotting/markerCorrelation.py
scimap/plotting/napariGater.py
scimap/plotting/pie.py
scimap/plotting/spatial_distance.py
scimap/plotting/spatial_interaction.py
scimap/plotting/spatial_pscore.py
scimap/plotting/spatial_scatterPlot.py
scimap/plotting/spatialInteractionNetwork.py
scimap/plotting/stacked_barplot.py
scimap/plotting/umap.py
scimap/plotting/voronoi.py
scimap/preprocessing/__init__.py
scimap/preprocessing/combat.py
scimap/preprocessing/log1p.py
scimap/preprocessing/mcmicro_to_scimap.py
scimap/preprocessing/ngraph.py
scimap/preprocessing/rescale.py
scimap/tests/_data/example_data.csv
scimap/tests/_data/example_data.h5ad
scimap/tests/_data/phenotype_workflow.csv
scimap/tests/expected_test_values/test_classify.pkl
scimap/tests/expected_test_values/test_cluster.pkl
scimap/tests/expected_test_values/test_combat.npz
scimap/tests/expected_test_values/test_foldchange.npz
scimap/tests/expected_test_values/test_log1p.npz
scimap/tests/expected_test_values/test_phenotype.pkl
scimap/tests/expected_test_values/test_rename.pkl
scimap-2.3.5.dist-info/entry_points.txt
scimap-2.3.5.dist-info/LICENSE
scimap-2.3.5.dist-info/METADATA
scimap-2.3.5.dist-info/WHEEL
scimap-2.3.5.dist-info/RECORD
