Metadata-Version: 2.1
Name: SCIMAP
Version: 2.3.5
Summary: Spatial Single-Cell Analysis Toolkit
Home-page: https://pypi.org/project/scimap/
License: MIT
Keywords: image analysis,multiplex imaging,single cell analysis
Author: Ajit Johnson Nirmal
Author-email: ajitjohnson.n@gmail.com
Requires-Python: >=3.9,<3.13
Classifier: Development Status :: 5 - Production/Stable
Classifier: License :: OSI Approved :: MIT License
Classifier: Natural Language :: English
Classifier: Operating System :: OS Independent
Classifier: Programming Language :: Python
Classifier: Programming Language :: Python :: 3
Classifier: Programming Language :: Python :: 3.9
Classifier: Programming Language :: Python :: 3.10
Classifier: Programming Language :: Python :: 3.11
Classifier: Programming Language :: Python :: 3.12
Provides-Extra: napari
Requires-Dist: PhenoGraph (>=1.5.7,<2.0.0)
Requires-Dist: TiffFile (>=2023.9.26,<2024.0.0)
Requires-Dist: anndata (>=0.10.5.post1,<0.11.0)
Requires-Dist: combat (>=0.3.3,<0.4.0)
Requires-Dist: dask[array] (>=2023.11.0,<2024.0.0)
Requires-Dist: gensim (>=4.3.2,<5.0.0)
Requires-Dist: llvmlite (>=0.41.1,<0.42.0)
Requires-Dist: matplotlib (>=3.8.1,<4.0.0)
Requires-Dist: mkdocs (>=1.5.3,<2.0.0)
Requires-Dist: mkdocs-material (>=9.4.8,<10.0.0)
Requires-Dist: mpl-scatter-density (>=0.7,<0.8)
Requires-Dist: napari (>=0.4.18,<0.5.0) ; extra == "napari"
Requires-Dist: napari-ome-zarr (>=0.4.0,<0.5.0) ; extra == "napari"
Requires-Dist: numba (>=0.58.1)
Requires-Dist: numpy (>=1.26.2,<2.0.0)
Requires-Dist: pandas (>=2.1.3,<3.0.0)
Requires-Dist: plotly (>=5.18.0,<6.0.0)
Requires-Dist: pyqt6 (>=6.6.1,<7.0.0) ; extra == "napari"
Requires-Dist: pytest (>=7.4.3,<8.0.0)
Requires-Dist: pytest-xvfb (>=3.0.0,<4.0.0)
Requires-Dist: scanpy (>=1.9.6,<2.0.0)
Requires-Dist: scikit-learn (>=1.4.2,<2.0.0)
Requires-Dist: scipy (>1.11.3,<=1.12.0)
Requires-Dist: seaborn (>=0.13.2,<0.14.0)
Requires-Dist: shapely (>=2.0.2,<3.0.0)
Requires-Dist: tifffile (>=2023.9.26,<2024.0.0)
Requires-Dist: zarr (==2.10.3)
Project-URL: Documentation, https://scimap.xyz
Project-URL: Repository, https://github.com/labsyspharm/scimap
